mentaws/__init__.py
mentaws/aws_operations.py
mentaws/config.py
mentaws/cryptographic_operations.py
mentaws/main.py
mentaws/operations.py
mentaws-0.6.1.dist-info/entry_points.txt
mentaws-0.6.1.dist-info/WHEEL
mentaws-0.6.1.dist-info/METADATA
mentaws-0.6.1.dist-info/RECORD
