Metadata-Version: 2.1
Name: mentaws
Version: 0.6.1
Summary: moMENTary AWS credentials
Home-page: https://github.com/keithrozario/mentaws
License: MIT
Keywords: aws,mentaws,tokens,credentials,temporary
Author: keithrozario
Author-email: keith@keithrozario.com
Requires-Python: >=3.6,<4.0
Classifier: Development Status :: 4 - Beta
Classifier: Intended Audience :: Developers
Classifier: License :: OSI Approved :: MIT License
Classifier: Natural Language :: English
Classifier: Programming Language :: Python :: 3
Classifier: Programming Language :: Python :: 3.6
Classifier: Programming Language :: Python :: 3.7
Classifier: Programming Language :: Python :: 3.8
Requires-Dist: PyYAML (>=5.3.1,<6.0.0)
Requires-Dist: boto3 (>=1.14.20,<2.0.0)
Requires-Dist: click (>=7.1.2,<8.0.0)
Requires-Dist: coveralls (>=1.11.1,<2.0.0)
Requires-Dist: cryptography (>=2.9.2,<3.0.0)
Requires-Dist: keyring (>=21.4.0,<22.0.0)
Requires-Dist: python-coveralls (>=2.9.3,<3.0.0)
Project-URL: Bug Tracker, https://github.com/keithrozario/mentaws/issues
Project-URL: Repository, https://github.com/keithrozario/mentaws
